myko/__init__.py
myko/myko.py
myko-0.0.6.dist-info/METADATA
myko-0.0.6.dist-info/WHEEL
myko-0.0.6.dist-info/licenses/LICENSE
myko-0.0.6.dist-info/RECORD
