Metadata-Version: 2.4
Name: myko
Version: 0.0.6
Summary: python tooling for the myko protocol
License-File: LICENSE
Requires-Python: >=3.11
Requires-Dist: asyncio>=3.4.3
Requires-Dist: websockets>=14.0
